{
    "name": "Highway",
    "theme_colors": {
        "foreground": "#ededed",
        "background": "#222225",
        "black": "#000000",
        "red": "#d00e18",
        "green": "#138034",
        "brown": "#ffcb3e",
        "blue": "#006bb3",
        "magenta": "#6b2775",
        "cyan": "#384564",
        "white": "#ededed",
        "light_black": "#5d504a",
        "light_red": "#f07e18",
        "light_green": "#b1d130",
        "light_brown": "#fff120",
        "light_blue": "#4fc2fd",
        "light_magenta": "#de0071",
        "light_cyan": "#5d504a",
        "light_white": "#ffffff"
    }
}